plain_json_logging/__init__.py
plain_json_logging-0.4.0.dist-info/LICENSE
plain_json_logging-0.4.0.dist-info/METADATA
plain_json_logging-0.4.0.dist-info/WHEEL
plain_json_logging-0.4.0.dist-info/top_level.txt
plain_json_logging-0.4.0.dist-info/RECORD
